rearden/__init__.py
rearden/decorators.py
rearden/grid_search.py
rearden/metrics.py
rearden/preprocessings.py
rearden/time_series.py
rearden/vizualizations.py
rearden-0.0.3.dist-info/LICENSE.txt
rearden-0.0.3.dist-info/METADATA
rearden-0.0.3.dist-info/WHEEL
rearden-0.0.3.dist-info/top_level.txt
rearden-0.0.3.dist-info/RECORD
