Metadata-Version: 2.1
Name: rearden
Version: 0.0.3
Summary: Library of useful data structures for data preprocessing, vizualizations and grid search
Author: Sergey Polivin
Author-email: s.polivin@gmail.com
License: MIT
Project-URL: Homepage, https://github.com/spolivin/rearden
Project-URL: Bug-Tracker, https://github.com/spolivin/rearden/issues
Project-URL: Pull-requests, https://github.com/spolivin/rearden/pulls
Project-URL: Source, https://github.com/spolivin/rearden/tree/master/src/rearden
Classifier: Development Status :: 2 - Pre-Alpha
Classifier: Intended Audience :: Developers
Classifier: License :: OSI Approved :: MIT License
Classifier: Programming Language :: Python :: 3
Classifier: Programming Language :: Python :: 3.9
Classifier: Programming Language :: Python :: 3.10
Classifier: Programming Language :: Python :: 3.11
Classifier: Topic :: Software Development :: Libraries
Classifier: Topic :: Software Development :: Libraries :: Python Modules
Requires-Python: >=3.9
License-File: LICENSE.txt
Requires-Dist: matplotlib >=3.3.4
Requires-Dist: pandas >=1.2.4
Requires-Dist: numpy >=1.24.3
Requires-Dist: scikit-learn >=1.1.3
Requires-Dist: seaborn >=0.11.1
Requires-Dist: statsmodels >=0.13.2
Provides-Extra: formatters
Requires-Dist: isort >=5.12.0 ; extra == 'formatters'
Requires-Dist: black >=23.3.0 ; extra == 'formatters'
Provides-Extra: linters
Requires-Dist: darglint >=1.8.1 ; extra == 'linters'
Requires-Dist: flake8 >=6.0.0 ; extra == 'linters'
Requires-Dist: flake8-bandit >=4.1.1 ; extra == 'linters'
Requires-Dist: flake8-bugbear >=23.7.10 ; extra == 'linters'
Requires-Dist: flake8-docstrings >=1.7.0 ; extra == 'linters'
Requires-Dist: flake8-builtins >=2.1.0 ; extra == 'linters'
Requires-Dist: flake8-eradicate >=1.5.0 ; extra == 'linters'
Requires-Dist: pre-commit >=3.3.2 ; extra == 'linters'
Provides-Extra: others
Requires-Dist: autoflake >=2.1.1 ; extra == 'others'
Requires-Dist: pyupgrade >=3.10.1 ; extra == 'others'
Requires-Dist: codespell >=2.2.4 ; extra == 'others'
